friday/__init__.py
friday/main.py
friday/cli/__init__.py
friday/cli/commands.py
friday/core/chat.py
friday/core/engine.py
friday/core/tools/base.py
friday/core/tools/bash.py
friday/core/tools/collection.py
friday/core/tools/edit.py
friday/license/__init__.py
friday/license/api_client.py
friday/license/cli.py
friday/license/crypto.py
friday/license/manager.py
friday/license/tools.py
friday/ui/__init__.py
friday/ui/loader.py
friday/ui/terminal.py
friday/ui/welcome.py
friday/utils/helpers.py
friday/utils/ocr.py
friday_ai_cli-1.2.2.dist-info/licenses/LICENSE
friday_ai_cli-1.2.2.dist-info/METADATA
friday_ai_cli-1.2.2.dist-info/WHEEL
friday_ai_cli-1.2.2.dist-info/entry_points.txt
friday_ai_cli-1.2.2.dist-info/top_level.txt
friday_ai_cli-1.2.2.dist-info/RECORD
