Metadata-Version: 2.4
Name: friday_ai_cli
Version: 1.2.2
Summary: FRIDAY AI CLI - Your AI-powered software development assistant built on Claude 3
Author: Yash Chouriya
Author-email: yashchouriya131@gmail.com
Keywords: cli,ai,development,assistant,claude,anthropic,coding assistant,developer tools,ai assistant
Classifier: Development Status :: 4 - Beta
Classifier: Environment :: Console
Classifier: Intended Audience :: Developers
Classifier: License :: OSI Approved :: MIT License
Classifier: Operating System :: OS Independent
Classifier: Programming Language :: Python :: 3
Classifier: Programming Language :: Python :: 3.11
Classifier: Topic :: Software Development :: Libraries :: Python Modules
Classifier: Topic :: Software Development :: Build Tools
Classifier: Topic :: Software Development :: Documentation
Requires-Python: >=3.11
License-File: LICENSE
Requires-Dist: annotated-types==0.7.0
Requires-Dist: anthropic==0.49.0
Requires-Dist: anyio==4.8.0
Requires-Dist: asyncio==3.4.3
Requires-Dist: backports.tarfile==1.2.0
Requires-Dist: certifi==2025.1.31
Requires-Dist: cffi==1.17.1
Requires-Dist: charset-normalizer==3.4.1
Requires-Dist: click==8.1.8
Requires-Dist: colorama==0.4.6
Requires-Dist: cryptography==42.0.5
Requires-Dist: decompyle3==3.9.2
Requires-Dist: distro==1.9.0
Requires-Dist: dotenv==0.9.9
Requires-Dist: h11==0.14.0
Requires-Dist: httpcore==1.0.7
Requires-Dist: httpx==0.28.1
Requires-Dist: idna==3.10
Requires-Dist: importlib_metadata==8.6.1
Requires-Dist: jaraco.classes==3.4.0
Requires-Dist: jaraco.context==6.0.1
Requires-Dist: jaraco.functools==4.1.0
Requires-Dist: jeepney==0.9.0
Requires-Dist: jiter==0.8.2
Requires-Dist: keyring==25.6.0
Requires-Dist: markdown-it-py==3.0.0
Requires-Dist: mdurl==0.1.2
Requires-Dist: more-itertools==10.6.0
Requires-Dist: pybytecode==0.1
Requires-Dist: pycparser==2.22
Requires-Dist: pydantic==2.10.6
Requires-Dist: pydantic_core==2.27.2
Requires-Dist: pyfiglet==1.0.2
Requires-Dist: Pygments==2.19.1
Requires-Dist: python-dotenv==1.0.1
Requires-Dist: python-magic==0.4.27
Requires-Dist: requests==2.32.3
Requires-Dist: rich==13.9.4
Requires-Dist: SecretStorage==3.3.3
Requires-Dist: shellingham==1.5.4
Requires-Dist: six==1.17.0
Requires-Dist: sniffio==1.3.1
Requires-Dist: spark-parser==1.8.9
Requires-Dist: typer==0.15.2
Requires-Dist: typing_extensions==4.12.2
Requires-Dist: uncompyle6==3.9.2
Requires-Dist: urllib3==2.3.0
Requires-Dist: xdis==6.1.3
Requires-Dist: zipp==3.21.0
Dynamic: author
Dynamic: author-email
Dynamic: classifier
Dynamic: description
Dynamic: description-content-type
Dynamic: keywords
Dynamic: license-file
Dynamic: requires-dist
Dynamic: requires-python
Dynamic: summary
